{
  "designName": "Issue733-kicad_complex_hierarchy_input_board.dsn",
  "unit": "UM",
  "resolution": 10.0,
  "layers": [
    {
      "index": 0,
      "name": "top_copper",
      "type": "plane"
    },
    {
      "index": 1,
      "name": "bottom_copper",
      "type": "signal"
    }
  ],
  "netClasses": [
    {
      "name": "default",
      "clearance": 3000.0,
      "traceWidth": 4000.0,
      "viaDiameter": 16510.0,
      "viaDrill": 8255.0,
      "netNames": [
        "/ampli_ht_horizontal/PIEZO_IN",
        "/ampli_ht_horizontal/PIEZO_OUT",
        "/ampli_ht_horizontal/S_OUT+",
        "/ampli_ht_horizontal/Vpil_0_3,3V",
        "/ampli_ht_vertical/PIEZO_IN",
        "/ampli_ht_vertical/PIEZO_OUT",
        "/ampli_ht_vertical/S_OUT+",
        "/ampli_ht_vertical/Vpil_0_3,3V",
        "Net-(U102-CAP+)",
        "Net-(U102-CAP-)",
        "Net-(C201-Pad2)",
        "Net-(C202-Pad1)",
        "Net-(U201B-+)",
        "Net-(C204-Pad1)",
        "Net-(C301-Pad2)",
        "Net-(C302-Pad1)",
        "Net-(U301B-+)",
        "Net-(C304-Pad1)",
        "Net-(D201-K)",
        "Net-(D202-K)",
        "Net-(D203-K)",
        "Net-(D203-A)",
        "Net-(D204-K)",
        "Net-(D301-K)",
        "Net-(D302-K)",
        "Net-(D303-A)",
        "Net-(D303-K)",
        "Net-(D304-K)",
        "Net-(Q201-E)",
        "Net-(Q202-E)",
        "Net-(Q203-E)",
        "Net-(Q204-E)",
        "Net-(Q204-B)",
        "Net-(Q301-E)",
        "+12V",
        "Net-(Q302-E)",
        "Net-(Q303-E)",
        "Net-(Q304-B)",
        "Net-(Q304-E)",
        "Net-(R212-Pad2)",
        "Net-(R213-Pad1)",
        "Net-(R312-Pad2)",
        "Net-(R313-Pad1)",
        "Net-(U201A--)",
        "Net-(U301A--)",
        "unconnected-(U102-LV-Pad6)",
        "unconnected-(U102-OSC-Pad7)"
      ]
    },
    {
      "name": "power",
      "clearance": 3000.0,
      "traceWidth": 6000.0,
      "viaDiameter": 16510.0,
      "viaDrill": 8255.0,
      "netNames": [
        "-VAA",
        "/12Vext",
        "GND",
        "HT",
        "VCC"
      ]
    }
  ],
  "nets": [
    {
      "id": 1,
      "name": "-VAA",
      "className": "power",
      "containsPlane": false
    },
    {
      "id": 2,
      "name": "/12Vext",
      "className": "power",
      "containsPlane": false
    },
    {
      "id": 3,
      "name": "/ampli_ht_horizontal/PIEZO_IN",
      "className": "default",
      "containsPlane": false
    },
    {
      "id": 4,
      "name": "/ampli_ht_horizontal/PIEZO_OUT",
      "className": "default",
      "containsPlane": false
    },
    {
      "id": 5,
      "name": "/ampli_ht_horizontal/S_OUT+",
      "className": "default",
      "containsPlane": false
    },
    {
      "id": 6,
      "name": "/ampli_ht_horizontal/Vpil_0_3,3V",
      "className": "default",
      "containsPlane": false
    },
    {
      "id": 7,
      "name": "/ampli_ht_vertical/PIEZO_IN",
      "className": "default",
      "containsPlane": false
    },
    {
      "id": 8,
      "name": "/ampli_ht_vertical/PIEZO_OUT",
      "className": "default",
      "containsPlane": false
    },
    {
      "id": 9,
      "name": "/ampli_ht_vertical/S_OUT+",
      "className": "default",
      "containsPlane": false
    },
    {
      "id": 10,
      "name": "/ampli_ht_vertical/Vpil_0_3,3V",
      "className": "default",
      "containsPlane": false
    },
    {
      "id": 11,
      "name": "GND",
      "className": "power",
      "containsPlane": false
    },
    {
      "id": 12,
      "name": "HT",
      "className": "power",
      "containsPlane": false
    },
    {
      "id": 13,
      "name": "Net-(U102-CAP+)",
      "className": "default",
      "containsPlane": false
    },
    {
      "id": 14,
      "name": "Net-(U102-CAP-)",
      "className": "default",
      "containsPlane": false
    },
    {
      "id": 15,
      "name": "Net-(C201-Pad2)",
      "className": "default",
      "containsPlane": false
    },
    {
      "id": 16,
      "name": "Net-(C202-Pad1)",
      "className": "default",
      "containsPlane": false
    },
    {
      "id": 17,
      "name": "Net-(U201B-+)",
      "className": "default",
      "containsPlane": false
    },
    {
      "id": 18,
      "name": "Net-(C204-Pad1)",
      "className": "default",
      "containsPlane": false
    },
    {
      "id": 19,
      "name": "Net-(C301-Pad2)",
      "className": "default",
      "containsPlane": false
    },
    {
      "id": 20,
      "name": "Net-(C302-Pad1)",
      "className": "default",
      "containsPlane": false
    },
    {
      "id": 21,
      "name": "Net-(U301B-+)",
      "className": "default",
      "containsPlane": false
    },
    {
      "id": 22,
      "name": "Net-(C304-Pad1)",
      "className": "default",
      "containsPlane": false
    },
    {
      "id": 23,
      "name": "Net-(D201-K)",
      "className": "default",
      "containsPlane": false
    },
    {
      "id": 24,
      "name": "Net-(D202-K)",
      "className": "default",
      "containsPlane": false
    },
    {
      "id": 25,
      "name": "Net-(D203-K)",
      "className": "default",
      "containsPlane": false
    },
    {
      "id": 26,
      "name": "Net-(D203-A)",
      "className": "default",
      "containsPlane": false
    },
    {
      "id": 27,
      "name": "Net-(D204-K)",
      "className": "default",
      "containsPlane": false
    },
    {
      "id": 28,
      "name": "Net-(D301-K)",
      "className": "default",
      "containsPlane": false
    },
    {
      "id": 29,
      "name": "Net-(D302-K)",
      "className": "default",
      "containsPlane": false
    },
    {
      "id": 30,
      "name": "Net-(D303-A)",
      "className": "default",
      "containsPlane": false
    },
    {
      "id": 31,
      "name": "Net-(D303-K)",
      "className": "default",
      "containsPlane": false
    },
    {
      "id": 32,
      "name": "Net-(D304-K)",
      "className": "default",
      "containsPlane": false
    },
    {
      "id": 33,
      "name": "VCC",
      "className": "power",
      "containsPlane": false
    },
    {
      "id": 34,
      "name": "Net-(Q201-E)",
      "className": "default",
      "containsPlane": false
    },
    {
      "id": 35,
      "name": "Net-(Q202-E)",
      "className": "default",
      "containsPlane": false
    },
    {
      "id": 36,
      "name": "Net-(Q203-E)",
      "className": "default",
      "containsPlane": false
    },
    {
      "id": 37,
      "name": "Net-(Q204-E)",
      "className": "default",
      "containsPlane": false
    },
    {
      "id": 38,
      "name": "Net-(Q204-B)",
      "className": "default",
      "containsPlane": false
    },
    {
      "id": 39,
      "name": "Net-(Q301-E)",
      "className": "default",
      "containsPlane": false
    },
    {
      "id": 40,
      "name": "+12V",
      "className": "default",
      "containsPlane": false
    },
    {
      "id": 41,
      "name": "Net-(Q302-E)",
      "className": "default",
      "containsPlane": false
    },
    {
      "id": 42,
      "name": "Net-(Q303-E)",
      "className": "default",
      "containsPlane": false
    },
    {
      "id": 43,
      "name": "Net-(Q304-B)",
      "className": "default",
      "containsPlane": false
    },
    {
      "id": 44,
      "name": "Net-(Q304-E)",
      "className": "default",
      "containsPlane": false
    },
    {
      "id": 45,
      "name": "Net-(R212-Pad2)",
      "className": "default",
      "containsPlane": false
    },
    {
      "id": 46,
      "name": "Net-(R213-Pad1)",
      "className": "default",
      "containsPlane": false
    },
    {
      "id": 47,
      "name": "Net-(R312-Pad2)",
      "className": "default",
      "containsPlane": false
    },
    {
      "id": 48,
      "name": "Net-(R313-Pad1)",
      "className": "default",
      "containsPlane": false
    },
    {
      "id": 49,
      "name": "Net-(U201A--)",
      "className": "default",
      "containsPlane": false
    },
    {
      "id": 50,
      "name": "Net-(U301A--)",
      "className": "default",
      "containsPlane": false
    },
    {
      "id": 51,
      "name": "unconnected-(U102-LV-Pad6)",
      "className": "default",
      "containsPlane": false
    },
    {
      "id": 52,
      "name": "unconnected-(U102-OSC-Pad7)",
      "className": "default",
      "containsPlane": false
    }
  ],
  "clearanceRules": [],
  "components": [],
  "outline": {
    "corners": [
      {
        "x": 879000.0,
        "y": 1318260.0
      },
      {
        "x": 1885950.0,
        "y": 1318260.0
      },
      {
        "x": 1885950.0,
        "y": 518160.0
      },
      {
        "x": 879000.0,
        "y": 518000.0
      }
    ],
    "clearance": 5000.0
  },
  "traces": [
    {
      "id": 1,
      "netName": "GND",
      "width": 6000.0,
      "layerIndex": 1,
      "points": [
        {
          "x": 1609750.0,
          "y": 1139608.0
        },
        {
          "x": 1625010.0,
          "y": 1139608.0
        },
        {
          "x": 1670787.0,
          "y": 1185385.0
        },
        {
          "x": 1670787.0,
          "y": 1234556.0
        },
        {
          "x": 1604863.0,
          "y": 1300480.0
        },
        {
          "x": 1431760.0,
          "y": 1300480.0
        }
      ]
    },
    {
      "id": 2,
      "netName": "GND",
      "width": 6000.0,
      "layerIndex": 1,
      "points": [
        {
          "x": 1492250.0,
          "y": 1238250.0
        },
        {
          "x": 1492250.0,
          "y": 1217819.0
        },
        {
          "x": 1570461.0,
          "y": 1139608.0
        },
        {
          "x": 1609750.0,
          "y": 1139608.0
        }
      ]
    },
    {
      "id": 3,
      "netName": "GND",
      "width": 6000.0,
      "layerIndex": 1,
      "points": [
        {
          "x": 1609750.0,
          "y": 1139608.0
        },
        {
          "x": 1609750.0,
          "y": 1041542.0
        }
      ]
    },
    {
      "id": 4,
      "netName": "-VAA",
      "width": 6000.0,
      "layerIndex": 1,
      "points": [
        {
          "x": 1149350.0,
          "y": 962660.0
        },
        {
          "x": 1149350.0,
          "y": 980677.0
        }
      ]
    },
    {
      "id": 5,
      "netName": "-VAA",
      "width": 6000.0,
      "layerIndex": 1,
      "points": [
        {
          "x": 1149350.0,
          "y": 980677.0
        },
        {
          "x": 1043542.0,
          "y": 1086485.0
        },
        {
          "x": 1019459.0,
          "y": 1086485.0
        },
        {
          "x": 1009101.0,
          "y": 1096843.0
        },
        {
          "x": 1009101.0,
          "y": 1133741.0
        },
        {
          "x": 1085844.0,
          "y": 1210484.0
        },
        {
          "x": 1149350.0,
          "y": 1210484.0
        }
      ]
    },
    {
      "id": 6,
      "netName": "GND",
      "width": 6000.0,
      "layerIndex": 1,
      "points": [
        {
          "x": 1609750.0,
          "y": 1041542.0
        },
        {
          "x": 1670538.0,
          "y": 980754.0
        },
        {
          "x": 1670538.0,
          "y": 954462.0
        },
        {
          "x": 1812000.0,
          "y": 813000.0
        }
      ]
    },
    {
      "id": 7,
      "netName": "HT",
      "width": 6000.0,
      "layerIndex": 1,
      "points": [
        {
          "x": 1235947.0,
          "y": 605790.0
        },
        {
          "x": 1235947.0,
          "y": 594529.0
        },
        {
          "x": 1248981.0,
          "y": 581495.0
        },
        {
          "x": 1504270.0,
          "y": 581495.0
        },
        {
          "x": 1604824.0,
          "y": 682049.0
        },
        {
          "x": 1604824.0,
          "y": 694802.0
        },
        {
          "x": 1616668.0,
          "y": 706646.0
        },
        {
          "x": 1616668.0,
          "y": 795653.0
        },
        {
          "x": 1538864.0,
          "y": 873457.0
        },
        {
          "x": 1530350.0,
          "y": 873457.0
        }
      ]
    },
    {
      "id": 8,
      "netName": "GND",
      "width": 6000.0,
      "layerIndex": 1,
      "points": [
        {
          "x": 1609750.0,
          "y": 1041542.0
        },
        {
          "x": 1490705.0,
          "y": 1041542.0
        },
        {
          "x": 1471721.5,
          "y": 1022558.5
        }
      ]
    },
    {
      "id": 9,
      "netName": "HT",
      "width": 6000.0,
      "layerIndex": 1,
      "points": [
        {
          "x": 1466850.0,
          "y": 1089660.0
        },
        {
          "x": 1482618.0,
          "y": 1089660.0
        },
        {
          "x": 1517650.0,
          "y": 1124692.0
        },
        {
          "x": 1517650.0,
          "y": 1150620.0
        }
      ]
    },
    {
      "id": 10,
      "netName": "HT",
      "width": 6000.0,
      "layerIndex": 1,
      "points": [
        {
          "x": 1217930.0,
          "y": 605790.0
        },
        {
          "x": 1235947.0,
          "y": 605790.0
        }
      ]
    },
    {
      "id": 11,
      "netName": "HT",
      "width": 6000.0,
      "layerIndex": 1,
      "points": [
        {
          "x": 1530350.0,
          "y": 873457.0
        },
        {
          "x": 1530350.0,
          "y": 899160.0
        }
      ]
    },
    {
      "id": 12,
      "netName": "HT",
      "width": 6000.0,
      "layerIndex": 1,
      "points": [
        {
          "x": 1454150.0,
          "y": 861060.0
        },
        {
          "x": 1517953.0,
          "y": 861060.0
        },
        {
          "x": 1530350.0,
          "y": 873457.0
        }
      ]
    },
    {
      "id": 13,
      "netName": "/ampli_ht_vertical/S_OUT+",
      "width": 4000.0,
      "layerIndex": 1,
      "points": [
        {
          "x": 984250.0,
          "y": 1254760.0
        },
        {
          "x": 1033893.0,
          "y": 1254760.0
        },
        {
          "x": 1079039.0,
          "y": 1299906.0
        },
        {
          "x": 1315294.0,
          "y": 1299906.0
        },
        {
          "x": 1358694.0,
          "y": 1256506.0
        },
        {
          "x": 1406175.0,
          "y": 1256506.0
        },
        {
          "x": 1430696.0,
          "y": 1281027.0
        },
        {
          "x": 1499317.0,
          "y": 1281027.0
        },
        {
          "x": 1562099.0,
          "y": 1218245.0
        },
        {
          "x": 1562099.0,
          "y": 1167130.0
        },
        {
          "x": 1562100.0,
          "y": 1167130.0
        }
      ]
    },
    {
      "id": 14,
      "netName": "Net-(Q202-E)",
      "width": 4000.0,
      "layerIndex": 1,
      "points": [
        {
          "x": 1600200.0,
          "y": 1242060.0
        },
        {
          "x": 1612217.0,
          "y": 1242060.0
        }
      ]
    },
    {
      "id": 15,
      "netName": "GND",
      "width": 6000.0,
      "layerIndex": 1,
      "points": [
        {
          "x": 1521015.0,
          "y": 687278.0
        },
        {
          "x": 1504950.0,
          "y": 703343.0
        }
      ]
    },
    {
      "id": 16,
      "netName": "GND",
      "width": 6000.0,
      "layerIndex": 1,
      "points": [
        {
          "x": 1416190.0,
          "y": 607060.0
        },
        {
          "x": 1516771.0,
          "y": 607060.0
        },
        {
          "x": 1544691.0,
          "y": 634980.0
        },
        {
          "x": 1544691.0,
          "y": 663602.0
        },
        {
          "x": 1521015.0,
          "y": 687278.0
        }
      ]
    },
    {
      "id": 17,
      "netName": "GND",
      "width": 6000.0,
      "layerIndex": 1,
      "points": [
        {
          "x": 1521015.0,
          "y": 687278.0
        },
        {
          "x": 1600200.0,
          "y": 766463.0
        },
        {
          "x": 1600200.0,
          "y": 783590.0
        }
      ]
    },
    {
      "id": 18,
      "netName": "Net-(D204-K)",
      "width": 4000.0,
      "layerIndex": 1,
      "points": [
        {
          "x": 1504950.0,
          "y": 1250950.0
        },
        {
          "x": 1487170.0,
          "y": 1268730.0
        },
        {
          "x": 1443990.0,
          "y": 1268730.0
        }
      ]
    },
    {
      "id": 19,
      "netName": "Net-(D204-K)",
      "width": 4000.0,
      "layerIndex": 1,
      "points": [
        {
          "x": 1409700.0,
          "y": 1235710.0
        },
        {
          "x": 1352550.0,
          "y": 1235710.0
        },
        {
          "x": 1330960.0,
          "y": 1257300.0
        }
      ]
    },
    {
      "id": 20,
      "netName": "GND",
      "width": 6000.0,
      "layerIndex": 1,
      "points": [
        {
          "x": 1492250.0,
          "y": 1238250.0
        },
        {
          "x": 1429965.0,
          "y": 1175965.0
        },
        {
          "x": 1429965.0,
          "y": 1159267.0
        },
        {
          "x": 1415909.0,
          "y": 1145211.0
        },
        {
          "x": 1385758.0,
          "y": 1145211.0
        },
        {
          "x": 1342631.0,
          "y": 1188338.0
        },
        {
          "x": 1253555.0,
          "y": 1188338.0
        },
        {
          "x": 1225550.0,
          "y": 1216343.0
        }
      ]
    },
    {
      "id": 21,
      "netName": "-VAA",
      "width": 6000.0,
      "layerIndex": 1,
      "points": [
        {
          "x": 1149350.0,
          "y": 1210484.0
        },
        {
          "x": 1225814.0,
          "y": 1134020.0
        },
        {
          "x": 1225814.0,
          "y": 880819.0
        },
        {
          "x": 1265516.0,
          "y": 841117.0
        },
        {
          "x": 1265516.0,
          "y": 807683.0
        },
        {
          "x": 1327823.0,
          "y": 745376.0
        },
        {
          "x": 1388289.0,
          "y": 745376.0
        },
        {
          "x": 1470488.0,
          "y": 663177.0
        },
        {
          "x": 1530350.0,
          "y": 663177.0
        }
      ]
    },
    {
      "id": 22,
      "netName": "-VAA",
      "width": 6000.0,
      "layerIndex": 1,
      "points": [
        {
          "x": 1149350.0,
          "y": 1233051.0
        },
        {
          "x": 1149350.0,
          "y": 1210484.0
        }
      ]
    },
    {
      "id": 23,
      "netName": "Net-(R212-Pad2)",
      "width": 4000.0,
      "layerIndex": 1,
      "points": [
        {
          "x": 1268730.0,
          "y": 1201420.0
        },
        {
          "x": 1268730.0,
          "y": 1216308.0
        },
        {
          "x": 1192735.0,
          "y": 1292303.0
        },
        {
          "x": 1106376.0,
          "y": 1292303.0
        },
        {
          "x": 1073150.0,
          "y": 1259077.0
        }
      ]
    },
    {
      "id": 24,
      "netName": "Net-(U201A--)",
      "width": 4000.0,
      "layerIndex": 1,
      "points": [
        {
          "x": 1098550.0,
          "y": 1225043.0
        },
        {
          "x": 963167.0,
          "y": 1225043.0
        },
        {
          "x": 958850.0,
          "y": 1229360.0
        }
      ]
    },
    {
      "id": 25,
      "netName": "+12V",
      "width": 4000.0,
      "layerIndex": 1,
      "points": [
        {
          "x": 1073150.0,
          "y": 1182877.0
        },
        {
          "x": 1155242.0,
          "y": 1182877.0
        },
        {
          "x": 1216175.0,
          "y": 1121944.0
        },
        {
          "x": 1216175.0,
          "y": 789497.0
        },
        {
          "x": 1193232.0,
          "y": 766554.0
        },
        {
          "x": 1178759.0,
          "y": 766554.0
        },
        {
          "x": 1157944.0,
          "y": 745739.0
        }
      ]
    },
    {
      "id": 26,
      "netName": "+12V",
      "width": 4000.0,
      "layerIndex": 1,
      "points": [
        {
          "x": 1157944.0,
          "y": 745739.0
        },
        {
          "x": 1127689.0,
          "y": 745739.0
        },
        {
          "x": 1073150.0,
          "y": 800278.0
        },
        {
          "x": 1073150.0,
          "y": 886460.0
        }
      ]
    },
    {
      "id": 27,
      "netName": "+12V",
      "width": 4000.0,
      "layerIndex": 1,
      "points": [
        {
          "x": 1157944.0,
          "y": 745739.0
        },
        {
          "x": 1157944.0,
          "y": 702113.0
        },
        {
          "x": 1160780.0,
          "y": 699277.0
        }
      ]
    },
    {
      "id": 28,
      "netName": "GND",
      "width": 6000.0,
      "layerIndex": 1,
      "points": [
        {
          "x": 1504950.0,
          "y": 721360.0
        },
        {
          "x": 1504950.0,
          "y": 703343.0
        }
      ]
    },
    {
      "id": 29,
      "netName": "-VAA",
      "width": 6000.0,
      "layerIndex": 1,
      "points": [
        {
          "x": 1530350.0,
          "y": 645160.0
        },
        {
          "x": 1530350.0,
          "y": 663177.0
        }
      ]
    },
    {
      "id": 30,
      "netName": "HT",
      "width": 6000.0,
      "layerIndex": 1,
      "points": [
        {
          "x": 1338533.0,
          "y": 1059180.0
        },
        {
          "x": 1324516.0,
          "y": 1045163.0
        },
        {
          "x": 1268756.0,
          "y": 1045163.0
        },
        {
          "x": 1242819.0,
          "y": 1019226.0
        },
        {
          "x": 1242819.0,
          "y": 877331.0
        },
        {
          "x": 1274533.0,
          "y": 845617.0
        },
        {
          "x": 1274533.0,
          "y": 811508.0
        },
        {
          "x": 1318920.0,
          "y": 767121.0
        },
        {
          "x": 1353608.0,
          "y": 767121.0
        },
        {
          "x": 1391440.0,
          "y": 804953.0
        },
        {
          "x": 1391440.0,
          "y": 823451.0
        }
      ]
    },
    {
      "id": 31,
      "netName": "-VAA",
      "width": 6000.0,
      "layerIndex": 1,
      "points": [
        {
          "x": 1149350.0,
          "y": 1242060.0
        },
        {
          "x": 1149350.0,
          "y": 1233051.0
        }
      ]
    },
    {
      "id": 32,
      "netName": "/ampli_ht_horizontal/Vpil_0_3,3V",
      "width": 4000.0,
      "layerIndex": 1,
      "points": [
        {
          "x": 1187450.0,
          "y": 814070.0
        },
        {
          "x": 1170305.0,
          "y": 831215.0
        },
        {
          "x": 1136638.0,
          "y": 831215.0
        },
        {
          "x": 1123950.0,
          "y": 843903.0
        },
        {
          "x": 1123950.0,
          "y": 886460.0
        }
      ]
    },
    {
      "id": 33,
      "netName": "+12V",
      "width": 4000.0,
      "layerIndex": 1,
      "points": [
        {
          "x": 1073150.0,
          "y": 1165860.0
        },
        {
          "x": 1073150.0,
          "y": 1182877.0
        }
      ]
    },
    {
      "id": 34,
      "netName": "HT",
      "width": 6000.0,
      "layerIndex": 1,
      "points": [
        {
          "x": 1199913.0,
          "y": 605790.0
        },
        {
          "x": 1163123.0,
          "y": 569000.0
        },
        {
          "x": 949000.0,
          "y": 569000.0
        }
      ]
    },
    {
      "id": 35,
      "netName": "GND",
      "width": 6000.0,
      "layerIndex": 1,
      "points": [
        {
          "x": 1282773.0,
          "y": 607060.0
        },
        {
          "x": 1282773.0,
          "y": 594473.0
        },
        {
          "x": 1279343.0,
          "y": 591043.0
        },
        {
          "x": 1252935.0,
          "y": 591043.0
        },
        {
          "x": 1250173.0,
          "y": 593805.0
        },
        {
          "x": 1250173.0,
          "y": 606184.0
        },
        {
          "x": 1219578.0,
          "y": 636779.0
        },
        {
          "x": 1050902.0,
          "y": 636779.0
        }
      ]
    },
    {
      "id": 36,
      "netName": "GND",
      "width": 6000.0,
      "layerIndex": 1,
      "points": [
        {
          "x": 1229360.0,
          "y": 695960.0
        },
        {
          "x": 1255233.0,
          "y": 695960.0
        },
        {
          "x": 1282773.0,
          "y": 668420.0
        },
        {
          "x": 1282773.0,
          "y": 607060.0
        }
      ]
    },
    {
      "id": 37,
      "netName": "GND",
      "width": 6000.0,
      "layerIndex": 1,
      "points": [
        {
          "x": 1400173.0,
          "y": 607060.0
        },
        {
          "x": 1282773.0,
          "y": 607060.0
        }
      ]
    },
    {
      "id": 38,
      "netName": "GND",
      "width": 6000.0,
      "layerIndex": 1,
      "points": [
        {
          "x": 1050902.0,
          "y": 636779.0
        },
        {
          "x": 1050902.0,
          "y": 690621.0
        },
        {
          "x": 1023480.0,
          "y": 718043.0
        }
      ]
    },
    {
      "id": 39,
      "netName": "GND",
      "width": 6000.0,
      "layerIndex": 1,
      "points": [
        {
          "x": 1037930.0,
          "y": 623807.0
        },
        {
          "x": 1050902.0,
          "y": 636779.0
        }
      ]
    },
    {
      "id": 40,
      "netName": "Net-(Q203-E)",
      "width": 4000.0,
      "layerIndex": 1,
      "points": [
        {
          "x": 1645333.0,
          "y": 1229360.0
        },
        {
          "x": 1620559.0,
          "y": 1254134.0
        },
        {
          "x": 1584921.0,
          "y": 1254134.0
        },
        {
          "x": 1574117.0,
          "y": 1243330.0
        }
      ]
    },
    {
      "id": 41,
      "netName": "Net-(U301B-+)",
      "width": 4000.0,
      "layerIndex": 1,
      "points": [
        {
          "x": 1149350.0,
          "y": 886460.0
        },
        {
          "x": 1149350.0,
          "y": 869443.0
        }
      ]
    },
    {
      "id": 42,
      "netName": "Net-(U301B-+)",
      "width": 4000.0,
      "layerIndex": 1,
      "points": [
        {
          "x": 1149350.0,
          "y": 869443.0
        },
        {
          "x": 1137920.0,
          "y": 858013.0
        },
        {
          "x": 1137920.0,
          "y": 848360.0
        }
      ]
    },
    {
      "id": 43,
      "netName": "+12V",
      "width": 4000.0,
      "layerIndex": 1,
      "points": [
        {
          "x": 1160780.0,
          "y": 683260.0
        },
        {
          "x": 1160780.0,
          "y": 699277.0
        }
      ]
    },
    {
      "id": 44,
      "netName": "/12Vext",
      "width": 6000.0,
      "layerIndex": 1,
      "points": [
        {
          "x": 948000.0,
          "y": 672983.0
        },
        {
          "x": 927887.0,
          "y": 652870.0
        },
        {
          "x": 927887.0,
          "y": 610308.0
        },
        {
          "x": 940334.0,
          "y": 597861.0
        },
        {
          "x": 965398.0,
          "y": 597861.0
        },
        {
          "x": 1033780.0,
          "y": 666243.0
        }
      ]
    },
    {
      "id": 45,
      "netName": "GND",
      "width": 6000.0,
      "layerIndex": 1,
      "points": [
        {
          "x": 946150.0,
          "y": 1166330.0
        },
        {
          "x": 919775.0,
          "y": 1139955.0
        },
        {
          "x": 919775.0,
          "y": 929225.0
        },
        {
          "x": 949000.0,
          "y": 900000.0
        }
      ]
    },
    {
      "id": 46,
      "netName": "Net-(Q201-E)",
      "width": 4000.0,
      "layerIndex": 1,
      "points": [
        {
          "x": 1390650.0,
          "y": 1089660.0
        },
        {
          "x": 1390650.0,
          "y": 1126519.0
        },
        {
          "x": 1345550.0,
          "y": 1171619.0
        },
        {
          "x": 1334224.0,
          "y": 1171619.0
        },
        {
          "x": 1324967.0,
          "y": 1162362.0
        },
        {
          "x": 1324967.0,
          "y": 1153160.0
        }
      ]
    },
    {
      "id": 47,
      "netName": "Net-(U301B-+)",
      "width": 4000.0,
      "layerIndex": 1,
      "points": [
        {
          "x": 1149350.0,
          "y": 903477.0
        },
        {
          "x": 1067005.0,
          "y": 903477.0
        },
        {
          "x": 1029970.0,
          "y": 866442.0
        },
        {
          "x": 1029970.0,
          "y": 849630.0
        }
      ]
    },
    {
      "id": 48,
      "netName": "GND",
      "width": 6000.0,
      "layerIndex": 1,
      "points": [
        {
          "x": 1179830.0,
          "y": 1013460.0
        },
        {
          "x": 1179830.0,
          "y": 1026477.0
        }
      ]
    },
    {
      "id": 49,
      "netName": "GND",
      "width": 6000.0,
      "layerIndex": 1,
      "points": [
        {
          "x": 1186650.0,
          "y": 1060450.0
        },
        {
          "x": 1186650.0,
          "y": 1033297.0
        },
        {
          "x": 1179830.0,
          "y": 1026477.0
        }
      ]
    },
    {
      "id": 50,
      "netName": "HT",
      "width": 6000.0,
      "layerIndex": 1,
      "points": [
        {
          "x": 1352550.0,
          "y": 1059180.0
        },
        {
          "x": 1338533.0,
          "y": 1059180.0
        }
      ]
    },
    {
      "id": 51,
      "netName": "Net-(Q304-B)",
      "width": 4000.0,
      "layerIndex": 1,
      "points": [
        {
          "x": 1256030.0,
          "y": 1013460.0
        },
        {
          "x": 1256030.0,
          "y": 989399.0
        },
        {
          "x": 1292929.0,
          "y": 952500.0
        },
        {
          "x": 1310640.0,
          "y": 952500.0
        }
      ]
    },
    {
      "id": 52,
      "netName": "HT",
      "width": 6000.0,
      "layerIndex": 1,
      "points": [
        {
          "x": 1391440.0,
          "y": 823451.0
        },
        {
          "x": 1416541.0,
          "y": 823451.0
        },
        {
          "x": 1454150.0,
          "y": 861060.0
        }
      ]
    },
    {
      "id": 53,
      "netName": "HT",
      "width": 6000.0,
      "layerIndex": 1,
      "points": [
        {
          "x": 1341167.0,
          "y": 788670.0
        },
        {
          "x": 1341167.0,
          "y": 792174.0
        },
        {
          "x": 1372444.0,
          "y": 823451.0
        },
        {
          "x": 1391440.0,
          "y": 823451.0
        }
      ]
    },
    {
      "id": 54,
      "netName": "GND",
      "width": 6000.0,
      "layerIndex": 1,
      "points": [
        {
          "x": 1471721.5,
          "y": 1022558.5
        },
        {
          "x": 1452880.0,
          "y": 1041400.0
        },
        {
          "x": 1430490.0,
          "y": 1041400.0
        }
      ]
    },
    {
      "id": 55,
      "netName": "GND",
      "width": 6000.0,
      "layerIndex": 1,
      "points": [
        {
          "x": 1484630.0,
          "y": 1009650.0
        },
        {
          "x": 1471721.5,
          "y": 1022558.5
        }
      ]
    },
    {
      "id": 56,
      "netName": "Net-(Q204-B)",
      "width": 4000.0,
      "layerIndex": 1,
      "points": [
        {
          "x": 1263650.0,
          "y": 1280160.0
        },
        {
          "x": 1308942.0,
          "y": 1280160.0
        },
        {
          "x": 1318260.0,
          "y": 1270842.0
        },
        {
          "x": 1318260.0,
          "y": 1244600.0
        }
      ]
    },
    {
      "id": 57,
      "netName": "GND",
      "width": 6000.0,
      "layerIndex": 1,
      "points": [
        {
          "x": 1416190.0,
          "y": 607060.0
        },
        {
          "x": 1400173.0,
          "y": 607060.0
        }
      ]
    },
    {
      "id": 58,
      "netName": "Net-(U201B-+)",
      "width": 4000.0,
      "layerIndex": 1,
      "points": [
        {
          "x": 1136650.0,
          "y": 1127760.0
        },
        {
          "x": 1136650.0,
          "y": 1125512.0
        },
        {
          "x": 1180534.0,
          "y": 1081628.0
        },
        {
          "x": 1191544.0,
          "y": 1081628.0
        },
        {
          "x": 1199541.0,
          "y": 1089625.0
        },
        {
          "x": 1199541.0,
          "y": 1099932.0
        },
        {
          "x": 1185711.0,
          "y": 1113762.0
        },
        {
          "x": 1182240.0,
          "y": 1113762.0
        },
        {
          "x": 1149350.0,
          "y": 1146652.0
        },
        {
          "x": 1149350.0,
          "y": 1165860.0
        }
      ]
    },
    {
      "id": 59,
      "netName": "GND",
      "width": 6000.0,
      "layerIndex": 1,
      "points": [
        {
          "x": 1186650.0,
          "y": 1060450.0
        },
        {
          "x": 1207573.0,
          "y": 1081373.0
        },
        {
          "x": 1207573.0,
          "y": 1106837.0
        },
        {
          "x": 1186650.0,
          "y": 1127760.0
        }
      ]
    },
    {
      "id": 60,
      "netName": "GND",
      "width": 6000.0,
      "layerIndex": 1,
      "points": [
        {
          "x": 1158974.5,
          "y": 905476.5
        },
        {
          "x": 1187920.0,
          "y": 876531.0
        },
        {
          "x": 1187920.0,
          "y": 848360.0
        }
      ]
    },
    {
      "id": 61,
      "netName": "GND",
      "width": 6000.0,
      "layerIndex": 1,
      "points": [
        {
          "x": 1035367.0,
          "y": 949960.0
        },
        {
          "x": 1048384.0,
          "y": 936943.0
        },
        {
          "x": 1127508.0,
          "y": 936943.0
        },
        {
          "x": 1158974.5,
          "y": 905476.5
        }
      ]
    },
    {
      "id": 62,
      "netName": "GND",
      "width": 6000.0,
      "layerIndex": 1,
      "points": [
        {
          "x": 1179830.0,
          "y": 1000443.0
        },
        {
          "x": 1198075.0,
          "y": 982198.0
        },
        {
          "x": 1198075.0,
          "y": 944577.0
        },
        {
          "x": 1158974.5,
          "y": 905476.5
        }
      ]
    },
    {
      "id": 63,
      "netName": "GND",
      "width": 6000.0,
      "layerIndex": 1,
      "points": [
        {
          "x": 1179830.0,
          "y": 1013460.0
        },
        {
          "x": 1179830.0,
          "y": 1000443.0
        }
      ]
    },
    {
      "id": 64,
      "netName": "Net-(D202-K)",
      "width": 4000.0,
      "layerIndex": 1,
      "points": [
        {
          "x": 1276350.0,
          "y": 1102677.0
        },
        {
          "x": 1289367.0,
          "y": 1102677.0
        },
        {
          "x": 1327150.0,
          "y": 1140460.0
        }
      ]
    },
    {
      "id": 65,
      "netName": "Net-(D202-K)",
      "width": 4000.0,
      "layerIndex": 1,
      "points": [
        {
          "x": 1225550.0,
          "y": 1153160.0
        },
        {
          "x": 1276033.0,
          "y": 1102677.0
        },
        {
          "x": 1276350.0,
          "y": 1102677.0
        }
      ]
    },
    {
      "id": 66,
      "netName": "GND",
      "width": 6000.0,
      "layerIndex": 1,
      "points": [
        {
          "x": 1187920.0,
          "y": 779780.0
        },
        {
          "x": 1201853.0,
          "y": 793713.0
        },
        {
          "x": 1201853.0,
          "y": 834427.0
        },
        {
          "x": 1187920.0,
          "y": 848360.0
        }
      ]
    },
    {
      "id": 67,
      "netName": "GND",
      "width": 6000.0,
      "layerIndex": 1,
      "points": [
        {
          "x": 1454150.0,
          "y": 810260.0
        },
        {
          "x": 1454150.0,
          "y": 797243.0
        }
      ]
    },
    {
      "id": 68,
      "netName": "+12V",
      "width": 4000.0,
      "layerIndex": 1,
      "points": [
        {
          "x": 1160780.0,
          "y": 683260.0
        },
        {
          "x": 1242060.0,
          "y": 683260.0
        }
      ]
    },
    {
      "id": 69,
      "netName": "GND",
      "width": 6000.0,
      "layerIndex": 1,
      "points": [
        {
          "x": 1022350.0,
          "y": 949960.0
        },
        {
          "x": 1035367.0,
          "y": 949960.0
        }
      ]
    },
    {
      "id": 70,
      "netName": "Net-(D303-A)",
      "width": 4000.0,
      "layerIndex": 1,
      "points": [
        {
          "x": 1454150.0,
          "y": 899160.0
        },
        {
          "x": 1441133.0,
          "y": 899160.0
        }
      ]
    },
    {
      "id": 71,
      "netName": "Net-(D303-A)",
      "width": 4000.0,
      "layerIndex": 1,
      "points": [
        {
          "x": 1441133.0,
          "y": 899160.0
        },
        {
          "x": 1390723.0,
          "y": 848750.0
        },
        {
          "x": 1372849.0,
          "y": 848750.0
        },
        {
          "x": 1339850.0,
          "y": 881749.0
        },
        {
          "x": 1339850.0,
          "y": 886460.0
        }
      ]
    },
    {
      "id": 72,
      "netName": "Net-(D304-K)",
      "width": 4000.0,
      "layerIndex": 1,
      "points": [
        {
          "x": 1416050.0,
          "y": 975360.0
        },
        {
          "x": 1403033.0,
          "y": 975360.0
        }
      ]
    },
    {
      "id": 73,
      "netName": "Net-(D304-K)",
      "width": 4000.0,
      "layerIndex": 1,
      "points": [
        {
          "x": 1323340.0,
          "y": 965200.0
        },
        {
          "x": 1392873.0,
          "y": 965200.0
        },
        {
          "x": 1403033.0,
          "y": 975360.0
        }
      ]
    },
    {
      "id": 74,
      "netName": "Net-(D203-A)",
      "width": 4000.0,
      "layerIndex": 1,
      "points": [
        {
          "x": 1454309.0,
          "y": 1159510.0
        },
        {
          "x": 1454309.0,
          "y": 1135953.0
        },
        {
          "x": 1395389.0,
          "y": 1077033.0
        },
        {
          "x": 1385782.0,
          "y": 1077033.0
        },
        {
          "x": 1339850.0,
          "y": 1122965.0
        },
        {
          "x": 1339850.0,
          "y": 1153160.0
        }
      ]
    },
    {
      "id": 75,
      "netName": "Net-(D203-A)",
      "width": 4000.0,
      "layerIndex": 1,
      "points": [
        {
          "x": 1454309.0,
          "y": 1159510.0
        },
        {
          "x": 1460817.0,
          "y": 1159510.0
        }
      ]
    },
    {
      "id": 76,
      "netName": "Net-(D203-A)",
      "width": 4000.0,
      "layerIndex": 1,
      "points": [
        {
          "x": 1447800.0,
          "y": 1159510.0
        },
        {
          "x": 1454309.0,
          "y": 1159510.0
        }
      ]
    },
    {
      "id": 77,
      "netName": "Net-(D304-K)",
      "width": 4000.0,
      "layerIndex": 1,
      "points": [
        {
          "x": 1497330.0,
          "y": 1022350.0
        },
        {
          "x": 1497330.0,
          "y": 998156.0
        },
        {
          "x": 1490632.0,
          "y": 991458.0
        },
        {
          "x": 1438052.0,
          "y": 991458.0
        },
        {
          "x": 1416050.0,
          "y": 1013460.0
        }
      ]
    },
    {
      "id": 78,
      "netName": "+12V",
      "width": 4000.0,
      "layerIndex": 1,
      "points": [
        {
          "x": 1242060.0,
          "y": 683260.0
        },
        {
          "x": 1266190.0,
          "y": 659130.0
        },
        {
          "x": 1266190.0,
          "y": 607060.0
        }
      ]
    },
    {
      "id": 79,
      "netName": "Net-(C201-Pad2)",
      "width": 4000.0,
      "layerIndex": 1,
      "points": [
        {
          "x": 1098550.0,
          "y": 1102360.0
        },
        {
          "x": 1128560.0,
          "y": 1102360.0
        },
        {
          "x": 1136180.0,
          "y": 1094740.0
        }
      ]
    },
    {
      "id": 80,
      "netName": "Net-(C301-Pad2)",
      "width": 4000.0,
      "layerIndex": 1,
      "points": [
        {
          "x": 1106170.0,
          "y": 822960.0
        },
        {
          "x": 1106170.0,
          "y": 849630.0
        }
      ]
    },
    {
      "id": 81,
      "netName": "Net-(Q302-E)",
      "width": 4000.0,
      "layerIndex": 1,
      "points": [
        {
          "x": 1612900.0,
          "y": 943610.0
        },
        {
          "x": 1550715.0,
          "y": 943610.0
        },
        {
          "x": 1515467.0,
          "y": 908362.0
        },
        {
          "x": 1515467.0,
          "y": 899160.0
        }
      ]
    },
    {
      "id": 82,
      "netName": "Net-(Q302-E)",
      "width": 4000.0,
      "layerIndex": 1,
      "points": [
        {
          "x": 1657350.0,
          "y": 923877.0
        },
        {
          "x": 1632633.0,
          "y": 923877.0
        },
        {
          "x": 1612900.0,
          "y": 943610.0
        }
      ]
    },
    {
      "id": 83,
      "netName": "Net-(Q302-E)",
      "width": 4000.0,
      "layerIndex": 1,
      "points": [
        {
          "x": 1612900.0,
          "y": 963343.0
        },
        {
          "x": 1612900.0,
          "y": 943610.0
        }
      ]
    },
    {
      "id": 84,
      "netName": "Net-(Q302-E)",
      "width": 4000.0,
      "layerIndex": 1,
      "points": [
        {
          "x": 1504950.0,
          "y": 899160.0
        },
        {
          "x": 1515467.0,
          "y": 899160.0
        }
      ]
    },
    {
      "id": 85,
      "netName": "Net-(Q301-E)",
      "width": 4000.0,
      "layerIndex": 1,
      "points": [
        {
          "x": 1314450.0,
          "y": 886460.0
        },
        {
          "x": 1324967.0,
          "y": 886460.0
        }
      ]
    },
    {
      "id": 86,
      "netName": "Net-(Q301-E)",
      "width": 4000.0,
      "layerIndex": 1,
      "points": [
        {
          "x": 1377950.0,
          "y": 861060.0
        },
        {
          "x": 1377950.0,
          "y": 873077.0
        }
      ]
    },
    {
      "id": 87,
      "netName": "Net-(Q301-E)",
      "width": 4000.0,
      "layerIndex": 1,
      "points": [
        {
          "x": 1377950.0,
          "y": 873077.0
        },
        {
          "x": 1346179.0,
          "y": 904848.0
        },
        {
          "x": 1334153.0,
          "y": 904848.0
        },
        {
          "x": 1324967.0,
          "y": 895662.0
        },
        {
          "x": 1324967.0,
          "y": 886460.0
        }
      ]
    },
    {
      "id": 88,
      "netName": "Net-(Q204-E)",
      "width": 4000.0,
      "layerIndex": 1,
      "points": [
        {
          "x": 1344930.0,
          "y": 1201420.0
        },
        {
          "x": 1337441.0,
          "y": 1201420.0
        },
        {
          "x": 1305560.0,
          "y": 1233301.0
        },
        {
          "x": 1305560.0,
          "y": 1257300.0
        }
      ]
    },
    {
      "id": 89,
      "netName": "Net-(R212-Pad2)",
      "width": 4000.0,
      "layerIndex": 1,
      "points": [
        {
          "x": 1073150.0,
          "y": 1242060.0
        },
        {
          "x": 1073150.0,
          "y": 1259077.0
        }
      ]
    },
    {
      "id": 90,
      "netName": "GND",
      "width": 6000.0,
      "layerIndex": 1,
      "points": [
        {
          "x": 1225550.0,
          "y": 1229360.0
        },
        {
          "x": 1212533.0,
          "y": 1229360.0
        }
      ]
    },
    {
      "id": 91,
      "netName": "GND",
      "width": 6000.0,
      "layerIndex": 1,
      "points": [
        {
          "x": 1187450.0,
          "y": 1280160.0
        },
        {
          "x": 1187450.0,
          "y": 1267143.0
        }
      ]
    },
    {
      "id": 92,
      "netName": "GND",
      "width": 6000.0,
      "layerIndex": 1,
      "points": [
        {
          "x": 1187450.0,
          "y": 1267143.0
        },
        {
          "x": 1212533.0,
          "y": 1242060.0
        },
        {
          "x": 1212533.0,
          "y": 1229360.0
        }
      ]
    },
    {
      "id": 93,
      "netName": "Net-(U201B-+)",
      "width": 4000.0,
      "layerIndex": 1,
      "points": [
        {
          "x": 1098550.0,
          "y": 1127760.0
        },
        {
          "x": 1136650.0,
          "y": 1127760.0
        }
      ]
    },
    {
      "id": 94,
      "netName": "Net-(C201-Pad2)",
      "width": 4000.0,
      "layerIndex": 1,
      "points": [
        {
          "x": 1022350.0,
          "y": 1127760.0
        },
        {
          "x": 1073150.0,
          "y": 1127760.0
        },
        {
          "x": 1098550.0,
          "y": 1102360.0
        }
      ]
    },
    {
      "id": 95,
      "netName": "Net-(Q201-E)",
      "width": 4000.0,
      "layerIndex": 1,
      "points": [
        {
          "x": 1314450.0,
          "y": 1153160.0
        },
        {
          "x": 1324967.0,
          "y": 1153160.0
        }
      ]
    },
    {
      "id": 96,
      "netName": "/ampli_ht_horizontal/PIEZO_OUT",
      "width": 4000.0,
      "layerIndex": 1,
      "points": [
        {
          "x": 1733550.0,
          "y": 975360.0
        },
        {
          "x": 1733550.0,
          "y": 911860.0
        }
      ]
    },
    {
      "id": 97,
      "netName": "Net-(Q303-E)",
      "width": 4000.0,
      "layerIndex": 1,
      "points": [
        {
          "x": 1568450.0,
          "y": 975360.0
        },
        {
          "x": 1580467.0,
          "y": 975360.0
        }
      ]
    },
    {
      "id": 98,
      "netName": "Net-(Q303-E)",
      "width": 4000.0,
      "layerIndex": 1,
      "points": [
        {
          "x": 1657350.0,
          "y": 975360.0
        },
        {
          "x": 1645333.0,
          "y": 975360.0
        }
      ]
    },
    {
      "id": 99,
      "netName": "Net-(Q303-E)",
      "width": 4000.0,
      "layerIndex": 1,
      "points": [
        {
          "x": 1645333.0,
          "y": 975360.0
        },
        {
          "x": 1633149.0,
          "y": 987544.0
        },
        {
          "x": 1592651.0,
          "y": 987544.0
        },
        {
          "x": 1580467.0,
          "y": 975360.0
        }
      ]
    },
    {
      "id": 100,
      "netName": "/ampli_ht_vertical/PIEZO_OUT",
      "width": 4000.0,
      "layerIndex": 1,
      "points": [
        {
          "x": 1733550.0,
          "y": 1229360.0
        },
        {
          "x": 1733550.0,
          "y": 1191260.0
        }
      ]
    },
    {
      "id": 101,
      "netName": "Net-(Q203-E)",
      "width": 4000.0,
      "layerIndex": 1,
      "points": [
        {
          "x": 1562100.0,
          "y": 1243330.0
        },
        {
          "x": 1574117.0,
          "y": 1243330.0
        }
      ]
    },
    {
      "id": 102,
      "netName": "Net-(Q203-E)",
      "width": 4000.0,
      "layerIndex": 1,
      "points": [
        {
          "x": 1657350.0,
          "y": 1229360.0
        },
        {
          "x": 1645333.0,
          "y": 1229360.0
        }
      ]
    },
    {
      "id": 103,
      "netName": "Net-(C202-Pad1)",
      "width": 4000.0,
      "layerIndex": 1,
      "points": [
        {
          "x": 1098550.0,
          "y": 1070610.0
        },
        {
          "x": 1066800.0,
          "y": 1102360.0
        },
        {
          "x": 1022350.0,
          "y": 1102360.0
        }
      ]
    },
    {
      "id": 104,
      "netName": "Net-(C304-Pad1)",
      "width": 4000.0,
      "layerIndex": 1,
      "points": [
        {
          "x": 1339850.0,
          "y": 1013460.0
        },
        {
          "x": 1352550.0,
          "y": 1013460.0
        },
        {
          "x": 1380490.0,
          "y": 1041400.0
        }
      ]
    },
    {
      "id": 105,
      "netName": "Net-(D302-K)",
      "width": 4000.0,
      "layerIndex": 1,
      "points": [
        {
          "x": 1327150.0,
          "y": 822960.0
        },
        {
          "x": 1327150.0,
          "y": 809943.0
        }
      ]
    },
    {
      "id": 106,
      "netName": "Net-(D302-K)",
      "width": 4000.0,
      "layerIndex": 1,
      "points": [
        {
          "x": 1377950.0,
          "y": 810260.0
        },
        {
          "x": 1342853.0,
          "y": 775163.0
        },
        {
          "x": 1322220.0,
          "y": 775163.0
        },
        {
          "x": 1314133.0,
          "y": 783250.0
        },
        {
          "x": 1314133.0,
          "y": 796926.0
        },
        {
          "x": 1327150.0,
          "y": 809943.0
        }
      ]
    },
    {
      "id": 107,
      "netName": "GND",
      "width": 6000.0,
      "layerIndex": 1,
      "points": [
        {
          "x": 1504950.0,
          "y": 721360.0
        },
        {
          "x": 1504950.0,
          "y": 746443.0
        },
        {
          "x": 1454150.0,
          "y": 797243.0
        }
      ]
    },
    {
      "id": 108,
      "netName": "Net-(U301B-+)",
      "width": 4000.0,
      "layerIndex": 1,
      "points": [
        {
          "x": 1149350.0,
          "y": 886460.0
        },
        {
          "x": 1149350.0,
          "y": 903477.0
        }
      ]
    },
    {
      "id": 109,
      "netName": "Net-(D202-K)",
      "width": 4000.0,
      "layerIndex": 1,
      "points": [
        {
          "x": 1276350.0,
          "y": 1089660.0
        },
        {
          "x": 1276350.0,
          "y": 1102677.0
        }
      ]
    },
    {
      "id": 110,
      "netName": "Net-(Q302-E)",
      "width": 4000.0,
      "layerIndex": 1,
      "points": [
        {
          "x": 1657350.0,
          "y": 911860.0
        },
        {
          "x": 1657350.0,
          "y": 923877.0
        }
      ]
    },
    {
      "id": 111,
      "netName": "Net-(Q302-E)",
      "width": 4000.0,
      "layerIndex": 1,
      "points": [
        {
          "x": 1612900.0,
          "y": 975360.0
        },
        {
          "x": 1612900.0,
          "y": 963343.0
        }
      ]
    },
    {
      "id": 112,
      "netName": "Net-(Q202-E)",
      "width": 4000.0,
      "layerIndex": 1,
      "points": [
        {
          "x": 1657350.0,
          "y": 1191260.0
        },
        {
          "x": 1657350.0,
          "y": 1203277.0
        }
      ]
    },
    {
      "id": 113,
      "netName": "Net-(Q202-E)",
      "width": 4000.0,
      "layerIndex": 1,
      "points": [
        {
          "x": 1612217.0,
          "y": 1242060.0
        },
        {
          "x": 1651000.0,
          "y": 1203277.0
        },
        {
          "x": 1657350.0,
          "y": 1203277.0
        }
      ]
    },
    {
      "id": 114,
      "netName": "Net-(R213-Pad1)",
      "width": 4000.0,
      "layerIndex": 1,
      "points": [
        {
          "x": 1028700.0,
          "y": 1267460.0
        },
        {
          "x": 946150.0,
          "y": 1267460.0
        },
        {
          "x": 933450.0,
          "y": 1254760.0
        }
      ]
    },
    {
      "id": 115,
      "netName": "Net-(R313-Pad1)",
      "width": 4000.0,
      "layerIndex": 1,
      "points": [
        {
          "x": 1022350.0,
          "y": 1026160.0
        },
        {
          "x": 958850.0,
          "y": 1026160.0
        },
        {
          "x": 933450.0,
          "y": 1000760.0
        }
      ]
    },
    {
      "id": 116,
      "netName": "GND",
      "width": 6000.0,
      "layerIndex": 1,
      "points": [
        {
          "x": 949000.0,
          "y": 900000.0
        },
        {
          "x": 927983.0,
          "y": 878983.0
        },
        {
          "x": 927983.0,
          "y": 764017.0
        },
        {
          "x": 948000.0,
          "y": 744000.0
        }
      ]
    },
    {
      "id": 117,
      "netName": "Net-(R312-Pad2)",
      "width": 4000.0,
      "layerIndex": 1,
      "points": [
        {
          "x": 1184910.0,
          "y": 949960.0
        },
        {
          "x": 1172893.0,
          "y": 949960.0
        }
      ]
    },
    {
      "id": 118,
      "netName": "Net-(R312-Pad2)",
      "width": 4000.0,
      "layerIndex": 1,
      "points": [
        {
          "x": 1073150.0,
          "y": 962660.0
        },
        {
          "x": 1073150.0,
          "y": 945643.0
        }
      ]
    },
    {
      "id": 119,
      "netName": "Net-(R312-Pad2)",
      "width": 4000.0,
      "layerIndex": 1,
      "points": [
        {
          "x": 1073150.0,
          "y": 945643.0
        },
        {
          "x": 1168576.0,
          "y": 945643.0
        },
        {
          "x": 1172893.0,
          "y": 949960.0
        }
      ]
    },
    {
      "id": 120,
      "netName": "Net-(U301A--)",
      "width": 4000.0,
      "layerIndex": 1,
      "points": [
        {
          "x": 1098550.0,
          "y": 962660.0
        },
        {
          "x": 1098550.0,
          "y": 979677.0
        }
      ]
    },
    {
      "id": 121,
      "netName": "Net-(U301A--)",
      "width": 4000.0,
      "layerIndex": 1,
      "points": [
        {
          "x": 1098550.0,
          "y": 979677.0
        },
        {
          "x": 963167.0,
          "y": 979677.0
        },
        {
          "x": 958850.0,
          "y": 975360.0
        }
      ]
    },
    {
      "id": 122,
      "netName": "VCC",
      "width": 6000.0,
      "layerIndex": 1,
      "points": [
        {
          "x": 1454150.0,
          "y": 663177.0
        },
        {
          "x": 1408667.0,
          "y": 708660.0
        },
        {
          "x": 1242060.0,
          "y": 708660.0
        }
      ]
    },
    {
      "id": 123,
      "netName": "Net-(U102-CAP+)",
      "width": 4000.0,
      "layerIndex": 1,
      "points": [
        {
          "x": 1397000.0,
          "y": 772160.0
        },
        {
          "x": 1412017.0,
          "y": 772160.0
        }
      ]
    },
    {
      "id": 124,
      "netName": "Net-(U102-CAP+)",
      "width": 4000.0,
      "layerIndex": 1,
      "points": [
        {
          "x": 1479550.0,
          "y": 721360.0
        },
        {
          "x": 1479550.0,
          "y": 738377.0
        }
      ]
    },
    {
      "id": 125,
      "netName": "Net-(U102-CAP+)",
      "width": 4000.0,
      "layerIndex": 1,
      "points": [
        {
          "x": 1479550.0,
          "y": 738377.0
        },
        {
          "x": 1445800.0,
          "y": 738377.0
        },
        {
          "x": 1412017.0,
          "y": 772160.0
        }
      ]
    },
    {
      "id": 126,
      "netName": "Net-(U102-CAP-)",
      "width": 4000.0,
      "layerIndex": 1,
      "points": [
        {
          "x": 1530350.0,
          "y": 721360.0
        },
        {
          "x": 1530350.0,
          "y": 738377.0
        }
      ]
    },
    {
      "id": 127,
      "netName": "Net-(U102-CAP-)",
      "width": 4000.0,
      "layerIndex": 1,
      "points": [
        {
          "x": 1530350.0,
          "y": 738377.0
        },
        {
          "x": 1547000.0,
          "y": 755027.0
        },
        {
          "x": 1547000.0,
          "y": 772160.0
        }
      ]
    },
    {
      "id": 128,
      "netName": "VCC",
      "width": 6000.0,
      "layerIndex": 1,
      "points": [
        {
          "x": 1454150.0,
          "y": 645160.0
        },
        {
          "x": 1454150.0,
          "y": 663177.0
        }
      ]
    },
    {
      "id": 129,
      "netName": "Net-(U201A--)",
      "width": 4000.0,
      "layerIndex": 1,
      "points": [
        {
          "x": 1098550.0,
          "y": 1242060.0
        },
        {
          "x": 1098550.0,
          "y": 1225043.0
        }
      ]
    },
    {
      "id": 130,
      "netName": "Net-(C204-Pad1)",
      "width": 4000.0,
      "layerIndex": 1,
      "points": [
        {
          "x": 1381760.0,
          "y": 1300480.0
        },
        {
          "x": 1367790.0,
          "y": 1286510.0
        },
        {
          "x": 1367790.0,
          "y": 1268730.0
        }
      ]
    },
    {
      "id": 131,
      "netName": "Net-(C202-Pad1)",
      "width": 4000.0,
      "layerIndex": 1,
      "points": [
        {
          "x": 1136650.0,
          "y": 1060450.0
        },
        {
          "x": 1108710.0,
          "y": 1060450.0
        },
        {
          "x": 1098550.0,
          "y": 1070610.0
        }
      ]
    },
    {
      "id": 132,
      "netName": "Net-(C302-Pad1)",
      "width": 4000.0,
      "layerIndex": 1,
      "points": [
        {
          "x": 1137920.0,
          "y": 779780.0
        },
        {
          "x": 1111250.0,
          "y": 779780.0
        },
        {
          "x": 1103630.0,
          "y": 787400.0
        }
      ]
    },
    {
      "id": 133,
      "netName": "GND",
      "width": 6000.0,
      "layerIndex": 1,
      "points": [
        {
          "x": 1225550.0,
          "y": 1229360.0
        },
        {
          "x": 1225550.0,
          "y": 1216343.0
        }
      ]
    },
    {
      "id": 134,
      "netName": "Net-(C301-Pad2)",
      "width": 4000.0,
      "layerIndex": 1,
      "points": [
        {
          "x": 1137450.0,
          "y": 814070.0
        },
        {
          "x": 1115060.0,
          "y": 814070.0
        },
        {
          "x": 1106170.0,
          "y": 822960.0
        }
      ]
    },
    {
      "id": 135,
      "netName": "/ampli_ht_vertical/Vpil_0_3,3V",
      "width": 4000.0,
      "layerIndex": 1,
      "points": [
        {
          "x": 1123950.0,
          "y": 1165860.0
        },
        {
          "x": 1123950.0,
          "y": 1148843.0
        }
      ]
    },
    {
      "id": 136,
      "netName": "/ampli_ht_vertical/Vpil_0_3,3V",
      "width": 4000.0,
      "layerIndex": 1,
      "points": [
        {
          "x": 1186180.0,
          "y": 1094740.0
        },
        {
          "x": 1186180.0,
          "y": 1096962.0
        },
        {
          "x": 1134299.0,
          "y": 1148843.0
        },
        {
          "x": 1123950.0,
          "y": 1148843.0
        }
      ]
    },
    {
      "id": 137,
      "netName": "HT",
      "width": 6000.0,
      "layerIndex": 1,
      "points": [
        {
          "x": 1327150.0,
          "y": 788670.0
        },
        {
          "x": 1341167.0,
          "y": 788670.0
        }
      ]
    },
    {
      "id": 138,
      "netName": "HT",
      "width": 6000.0,
      "layerIndex": 1,
      "points": [
        {
          "x": 1352550.0,
          "y": 1059180.0
        },
        {
          "x": 1436370.0,
          "y": 1059180.0
        },
        {
          "x": 1466850.0,
          "y": 1089660.0
        }
      ]
    },
    {
      "id": 139,
      "netName": "Net-(D201-K)",
      "width": 4000.0,
      "layerIndex": 1,
      "points": [
        {
          "x": 1352550.0,
          "y": 1089660.0
        },
        {
          "x": 1339533.0,
          "y": 1089660.0
        }
      ]
    },
    {
      "id": 140,
      "netName": "Net-(D201-K)",
      "width": 4000.0,
      "layerIndex": 1,
      "points": [
        {
          "x": 1339533.0,
          "y": 1089660.0
        },
        {
          "x": 1309053.0,
          "y": 1059180.0
        },
        {
          "x": 1276350.0,
          "y": 1059180.0
        }
      ]
    },
    {
      "id": 141,
      "netName": "Net-(D203-A)",
      "width": 4000.0,
      "layerIndex": 1,
      "points": [
        {
          "x": 1460817.0,
          "y": 1159510.0
        },
        {
          "x": 1482407.0,
          "y": 1137920.0
        },
        {
          "x": 1504950.0,
          "y": 1137920.0
        }
      ]
    },
    {
      "id": 142,
      "netName": "Net-(D304-K)",
      "width": 4000.0,
      "layerIndex": 1,
      "points": [
        {
          "x": 1416050.0,
          "y": 975360.0
        },
        {
          "x": 1416050.0,
          "y": 1013460.0
        }
      ]
    },
    {
      "id": 143,
      "netName": "Net-(D204-K)",
      "width": 4000.0,
      "layerIndex": 1,
      "points": [
        {
          "x": 1409700.0,
          "y": 1235710.0
        },
        {
          "x": 1422717.0,
          "y": 1235710.0
        }
      ]
    },
    {
      "id": 144,
      "netName": "Net-(D204-K)",
      "width": 4000.0,
      "layerIndex": 1,
      "points": [
        {
          "x": 1422717.0,
          "y": 1235710.0
        },
        {
          "x": 1422717.0,
          "y": 1247457.0
        },
        {
          "x": 1443990.0,
          "y": 1268730.0
        }
      ]
    },
    {
      "id": 145,
      "netName": "Net-(D203-K)",
      "width": 4000.0,
      "layerIndex": 1,
      "points": [
        {
          "x": 1409700.0,
          "y": 1159510.0
        },
        {
          "x": 1409700.0,
          "y": 1172527.0
        }
      ]
    },
    {
      "id": 146,
      "netName": "Net-(D203-K)",
      "width": 4000.0,
      "layerIndex": 1,
      "points": [
        {
          "x": 1409700.0,
          "y": 1172527.0
        },
        {
          "x": 1447800.0,
          "y": 1210627.0
        },
        {
          "x": 1447800.0,
          "y": 1235710.0
        }
      ]
    },
    {
      "id": 147,
      "netName": "Net-(D303-K)",
      "width": 4000.0,
      "layerIndex": 1,
      "points": [
        {
          "x": 1454150.0,
          "y": 975360.0
        },
        {
          "x": 1454150.0,
          "y": 962343.0
        }
      ]
    },
    {
      "id": 148,
      "netName": "Net-(D303-K)",
      "width": 4000.0,
      "layerIndex": 1,
      "points": [
        {
          "x": 1454150.0,
          "y": 962343.0
        },
        {
          "x": 1416050.0,
          "y": 924243.0
        },
        {
          "x": 1416050.0,
          "y": 899160.0
        }
      ]
    },
    {
      "id": 149,
      "netName": "Net-(D303-A)",
      "width": 4000.0,
      "layerIndex": 1,
      "points": [
        {
          "x": 1454150.0,
          "y": 899160.0
        },
        {
          "x": 1467167.0,
          "y": 899160.0
        }
      ]
    },
    {
      "id": 150,
      "netName": "Net-(D303-A)",
      "width": 4000.0,
      "layerIndex": 1,
      "points": [
        {
          "x": 1467167.0,
          "y": 899160.0
        },
        {
          "x": 1479867.0,
          "y": 886460.0
        },
        {
          "x": 1517650.0,
          "y": 886460.0
        }
      ]
    },
    {
      "id": 151,
      "netName": "Net-(D302-K)",
      "width": 4000.0,
      "layerIndex": 1,
      "points": [
        {
          "x": 1327150.0,
          "y": 822960.0
        },
        {
          "x": 1327150.0,
          "y": 873760.0
        }
      ]
    },
    {
      "id": 152,
      "netName": "Net-(D301-K)",
      "width": 4000.0,
      "layerIndex": 1,
      "points": [
        {
          "x": 1250950.0,
          "y": 822960.0
        },
        {
          "x": 1250950.0,
          "y": 788670.0
        }
      ]
    },
    {
      "id": 153,
      "netName": "HT",
      "width": 6000.0,
      "layerIndex": 1,
      "points": [
        {
          "x": 1217930.0,
          "y": 605790.0
        },
        {
          "x": 1199913.0,
          "y": 605790.0
        }
      ]
    },
    {
      "id": 154,
      "netName": "GND",
      "width": 6000.0,
      "layerIndex": 1,
      "points": [
        {
          "x": 1037930.0,
          "y": 605790.0
        },
        {
          "x": 1037930.0,
          "y": 623807.0
        }
      ]
    },
    {
      "id": 155,
      "netName": "GND",
      "width": 6000.0,
      "layerIndex": 1,
      "points": [
        {
          "x": 1023480.0,
          "y": 734060.0
        },
        {
          "x": 1023480.0,
          "y": 718043.0
        }
      ]
    },
    {
      "id": 156,
      "netName": "/12Vext",
      "width": 6000.0,
      "layerIndex": 1,
      "points": [
        {
          "x": 1033780.0,
          "y": 683260.0
        },
        {
          "x": 1033780.0,
          "y": 666243.0
        }
      ]
    },
    {
      "id": 157,
      "netName": "/12Vext",
      "width": 6000.0,
      "layerIndex": 1,
      "points": [
        {
          "x": 948000.0,
          "y": 694000.0
        },
        {
          "x": 948000.0,
          "y": 672983.0
        }
      ]
    },
    {
      "id": 158,
      "netName": "GND",
      "width": 6000.0,
      "layerIndex": 1,
      "points": [
        {
          "x": 969017.0,
          "y": 734060.0
        },
        {
          "x": 957940.0,
          "y": 734060.0
        },
        {
          "x": 948000.0,
          "y": 744000.0
        }
      ]
    },
    {
      "id": 159,
      "netName": "GND",
      "width": 6000.0,
      "layerIndex": 1,
      "points": [
        {
          "x": 1023480.0,
          "y": 734060.0
        },
        {
          "x": 969017.0,
          "y": 734060.0
        }
      ]
    },
    {
      "id": 160,
      "netName": "GND",
      "width": 6000.0,
      "layerIndex": 1,
      "points": [
        {
          "x": 969017.0,
          "y": 734060.0
        },
        {
          "x": 969017.0,
          "y": 639017.0
        },
        {
          "x": 949000.0,
          "y": 619000.0
        }
      ]
    },
    {
      "id": 161,
      "netName": "/ampli_ht_vertical/PIEZO_IN",
      "width": 4000.0,
      "layerIndex": 1,
      "points": [
        {
          "x": 946150.0,
          "y": 1116330.0
        },
        {
          "x": 966167.0,
          "y": 1116330.0
        }
      ]
    },
    {
      "id": 162,
      "netName": "/ampli_ht_vertical/PIEZO_IN",
      "width": 4000.0,
      "layerIndex": 1,
      "points": [
        {
          "x": 1022350.0,
          "y": 1070610.0
        },
        {
          "x": 1010333.0,
          "y": 1070610.0
        }
      ]
    },
    {
      "id": 163,
      "netName": "/ampli_ht_vertical/PIEZO_IN",
      "width": 4000.0,
      "layerIndex": 1,
      "points": [
        {
          "x": 966167.0,
          "y": 1116330.0
        },
        {
          "x": 966167.0,
          "y": 1114776.0
        },
        {
          "x": 1010333.0,
          "y": 1070610.0
        }
      ]
    },
    {
      "id": 164,
      "netName": "GND",
      "width": 6000.0,
      "layerIndex": 1,
      "points": [
        {
          "x": 1028700.0,
          "y": 1191260.0
        },
        {
          "x": 1015683.0,
          "y": 1191260.0
        }
      ]
    },
    {
      "id": 165,
      "netName": "GND",
      "width": 6000.0,
      "layerIndex": 1,
      "points": [
        {
          "x": 946150.0,
          "y": 1166330.0
        },
        {
          "x": 990753.0,
          "y": 1166330.0
        },
        {
          "x": 1015683.0,
          "y": 1191260.0
        }
      ]
    },
    {
      "id": 166,
      "netName": "/ampli_ht_horizontal/PIEZO_IN",
      "width": 4000.0,
      "layerIndex": 1,
      "points": [
        {
          "x": 1027430.0,
          "y": 787400.0
        },
        {
          "x": 1027430.0,
          "y": 799417.0
        }
      ]
    },
    {
      "id": 167,
      "netName": "/ampli_ht_horizontal/PIEZO_IN",
      "width": 4000.0,
      "layerIndex": 1,
      "points": [
        {
          "x": 949000.0,
          "y": 850000.0
        },
        {
          "x": 969017.0,
          "y": 850000.0
        }
      ]
    },
    {
      "id": 168,
      "netName": "/ampli_ht_horizontal/PIEZO_IN",
      "width": 4000.0,
      "layerIndex": 1,
      "points": [
        {
          "x": 969017.0,
          "y": 850000.0
        },
        {
          "x": 1019600.0,
          "y": 799417.0
        },
        {
          "x": 1027430.0,
          "y": 799417.0
        }
      ]
    },
    {
      "id": 169,
      "netName": "GND",
      "width": 6000.0,
      "layerIndex": 1,
      "points": [
        {
          "x": 949000.0,
          "y": 900000.0
        },
        {
          "x": 998960.0,
          "y": 949960.0
        },
        {
          "x": 1022350.0,
          "y": 949960.0
        }
      ]
    },
    {
      "id": 170,
      "netName": "GND",
      "width": 6000.0,
      "layerIndex": 1,
      "points": [
        {
          "x": 1812000.0,
          "y": 813000.0
        },
        {
          "x": 1833165.0,
          "y": 834165.0
        },
        {
          "x": 1833165.0,
          "y": 1053335.0
        },
        {
          "x": 1811925.0,
          "y": 1074575.0
        }
      ]
    },
    {
      "id": 171,
      "netName": "VCC",
      "width": 6000.0,
      "layerIndex": 1,
      "points": [
        {
          "x": 1242060.0,
          "y": 708660.0
        },
        {
          "x": 1231043.0,
          "y": 708660.0
        }
      ]
    },
    {
      "id": 172,
      "netName": "VCC",
      "width": 6000.0,
      "layerIndex": 1,
      "points": [
        {
          "x": 1173480.0,
          "y": 734060.0
        },
        {
          "x": 1205643.0,
          "y": 734060.0
        },
        {
          "x": 1231043.0,
          "y": 708660.0
        }
      ]
    }
  ],
  "vias": [],
  "conductionAreas": []
}